dequantor/__init__.py
dequantor/callbacks.py
dequantor/configuration_utils.py
dequantor/dependency_versions_check.py
dequantor/dependency_versions_table.py
dequantor/image_processor.py
dequantor/optimization.py
dequantor/py.typed
dequantor/training_utils.py
dequantor/video_processor.py
dequantor/commands/__init__.py
dequantor/commands/custom_blocks.py
dequantor/commands/diffusers_cli.py
dequantor/commands/env.py
dequantor/commands/fp16_safetensors.py
dequantor/experimental/README.md
dequantor/experimental/__init__.py
dequantor/experimental/rl/__init__.py
dequantor/experimental/rl/value_guided_sampling.py
dequantor/guiders/__init__.py
dequantor/guiders/adaptive_projected_guidance.py
dequantor/guiders/adaptive_projected_guidance_mix.py
dequantor/guiders/auto_guidance.py
dequantor/guiders/classifier_free_guidance.py
dequantor/guiders/classifier_free_zero_star_guidance.py
dequantor/guiders/frequency_decoupled_guidance.py
dequantor/guiders/guider_utils.py
dequantor/guiders/perturbed_attention_guidance.py
dequantor/guiders/skip_layer_guidance.py
dequantor/guiders/smoothed_energy_guidance.py
dequantor/guiders/tangential_classifier_free_guidance.py
dequantor/hooks/__init__.py
dequantor/hooks/_common.py
dequantor/hooks/_helpers.py
dequantor/hooks/context_parallel.py
dequantor/hooks/faster_cache.py
dequantor/hooks/first_block_cache.py
dequantor/hooks/group_offloading.py
dequantor/hooks/hooks.py
dequantor/hooks/layer_skip.py
dequantor/hooks/layerwise_casting.py
dequantor/hooks/pyramid_attention_broadcast.py
dequantor/hooks/smoothed_energy_guidance_utils.py
dequantor/hooks/taylorseer_cache.py
dequantor/hooks/utils.py
dequantor/loaders/__init__.py
dequantor/loaders/ip_adapter.py
dequantor/loaders/lora_base.py
dequantor/loaders/lora_conversion_utils.py
dequantor/loaders/lora_pipeline.py
dequantor/loaders/peft.py
dequantor/loaders/single_file.py
dequantor/loaders/single_file_model.py
dequantor/loaders/single_file_utils.py
dequantor/loaders/textual_inversion.py
dequantor-0.1.3.dist-info/LICENSE
dequantor-0.1.3.dist-info/WHEEL
dequantor-0.1.3.dist-info/METADATA
dequantor-0.1.3.dist-info/RECORD
