Metadata-Version: 2.1
Name: dequantor
Version: 0.1.3
Summary: model runner and dequantor
Author-email: calcuis <info@calcu.io>
Classifier: License :: OSI Approved :: Apache Software License
Project-URL: Repository, https://github.com/calcuis/dequantor
